pynfeintegration/__init__.py
pynfeintegration/base/__init__.py
pynfeintegration/base/classes/__init__.py
pynfeintegration/base/classes/base_entity.py
pynfeintegration/base/classes/base_requester.py
pynfeintegration/certificates/__init__.py
pynfeintegration/certificates/pfx_certificate.py
pynfeintegration/constantes/__init__.py
pynfeintegration/constantes/codes.py
pynfeintegration/constantes/contingency.py
pynfeintegration/constantes/name_spaces.py
pynfeintegration/constantes/versions.py
pynfeintegration/nfe/__init__.py
pynfeintegration/nfe/nfe_requester.py
pynfeintegration/nfe/xml_builders/__init__.py
pynfeintegration/nfe/xml_builders/nfe_xml_builder.py
pynfeintegration/nfe/xml_builders/nfe_xml_builder_base.py
pynfeintegration/nfe/xml_builders/nfe_xml_builder_distribution.py
pynfeintegration/nfe/xml_builders/nfe_xml_builder_factory.py
pynfeintegration/nfe/xml_builders/nfe_xml_builder_status.py
pynfeintegration/utils/__init__.py
pynfeintegration/utils/nfe_converter.py
pynfeintegration/webservices/__init__.py
pynfeintegration/webservices/nfce.py
pynfeintegration/webservices/nfe.py
pynfeintegration/webservices/nfse.py
pynfeintegration/webservices/web_service_model.py
PyNfeIntegration-1.1.0.dist-info/LICENSE.txt
PyNfeIntegration-1.1.0.dist-info/METADATA
PyNfeIntegration-1.1.0.dist-info/WHEEL
PyNfeIntegration-1.1.0.dist-info/top_level.txt
PyNfeIntegration-1.1.0.dist-info/RECORD
