Metadata-Version: 2.1
Name: PyNfeIntegration
Version: 1.1.0
Summary: PyNfeIntegration is a library that implement consults to invoices generate against some CNPJ
Home-page: https://github.com/ADD01-TECH/py-nfe-integration
Author: Cristiano dos Santos Lemos
Author-email: cristianolemos@somma-it.com
License: MIT
Keywords: nfe,sped
Classifier: Development Status :: 5 - Production/Stable
Classifier: Environment :: Plugins
Classifier: Intended Audience :: Developers
Classifier: License :: OSI Approved :: MIT License
Classifier: Operating System :: OS Independent
Classifier: Programming Language :: Python
Classifier: Topic :: Software Development :: Libraries :: Python Modules
Requires: lxml(>=4.9.2)
Requires: pyOpenSSL(>=23.1.1)
Requires: qrcode(>=5.3)
Requires: requests(>=2.30.0)
License-File: LICENSE.txt
